.gitignore
MANIFEST.in
README.rst
bootstrap.py
buildout.cfg
setup.cfg
setup.py
docs/HISTORY.txt
docs/LICENSE.GPL
docs/LICENSE.txt
src/collective/__init__.py
src/collective.overridemailrecipients.egg-info/PKG-INFO
src/collective.overridemailrecipients.egg-info/SOURCES.txt
src/collective.overridemailrecipients.egg-info/dependency_links.txt
src/collective.overridemailrecipients.egg-info/entry_points.txt
src/collective.overridemailrecipients.egg-info/namespace_packages.txt
src/collective.overridemailrecipients.egg-info/not-zip-safe
src/collective.overridemailrecipients.egg-info/paster_plugins.txt
src/collective.overridemailrecipients.egg-info/requires.txt
src/collective.overridemailrecipients.egg-info/top_level.txt
src/collective/overridemailrecipients/__init__.py
src/collective/overridemailrecipients/configpanel.py
src/collective/overridemailrecipients/configure.zcml
src/collective/overridemailrecipients/interfaces.py
src/collective/overridemailrecipients/patches.py
src/collective/overridemailrecipients/testing.py
src/collective/overridemailrecipients/testing.zcml
src/collective/overridemailrecipients/profiles/default/controlpanel.xml
src/collective/overridemailrecipients/profiles/default/metadata.xml
src/collective/overridemailrecipients/profiles/default/registry.xml
src/collective/overridemailrecipients/tests/__init__.py
src/collective/overridemailrecipients/tests/test_overridemailrecipients.py