Metadata-Version: 1.0
Name: collective.overridemailrecipients
Version: 1.0.1
Summary: UNKNOWN
Home-page: http://svn.plone.org/svn/collective/
Author: Goldmund, Wyldebeast & Wunderliebe
Author-email: info@gw20e.com
License: GPL
Platform: UNKNOWN
Classifier: Topic :: Software Development :: Libraries :: Python Modules
Classifier: License :: OSI Approved :: GNU General Public License (GPL)
Classifier: Operating System :: OS Independent
Classifier: Programming Language :: Python
Classifier: Environment :: Web Environment
Classifier: Framework :: Plone
Classifier: Framework :: Plone :: 4.0
Classifier: Framework :: Plone :: 4.1
Classifier: Framework :: Plone :: 4.2
